ideabox.policy-3.4.18-py3.10-nspkg.pth
ideabox/policy/__init__.py
ideabox/policy/adapters.py
ideabox/policy/configure.zcml
ideabox/policy/interfaces.py
ideabox/policy/permissions.zcml
ideabox/policy/setuphandlers.py
ideabox/policy/testing.py
ideabox/policy/testing.zcml
ideabox/policy/userdataschema.py
ideabox/policy/utils.py
ideabox/policy/vocabularies.py
ideabox/policy/vocabularies.zcml
ideabox/policy/browser/__init__.py
ideabox/policy/browser/comment.py
ideabox/policy/browser/configure.zcml
ideabox/policy/browser/controlpanel.py
ideabox/policy/browser/folder.py
ideabox/policy/browser/project.py
ideabox/policy/browser/project_submission.py
ideabox/policy/browser/rating.py
ideabox/policy/browser/register.py
ideabox/policy/browser/viewlet.py
ideabox/policy/browser/workflow.py
ideabox/policy/browser/overrides/.gitkeep
ideabox/policy/browser/overrides/cioppino.twothumbs.browser.templates.login_to_rate.pt
ideabox/policy/browser/overrides/plone.app.contenttypes.browser.templates.newsitem.pt
ideabox/policy/browser/static/.gitkeep
ideabox/policy/browser/static/ideabox-compiled.css
ideabox/policy/browser/static/ideabox-compiled.js
ideabox/policy/browser/static/ideabox.js
ideabox/policy/browser/static/ideabox.less
ideabox/policy/browser/templates/project_submission.pt
ideabox/policy/browser/templates/project_summary.pt
ideabox/policy/browser/templates/rating.pt
ideabox/policy/browser/templates/register_form.pt
ideabox/policy/browser/templates/user_menu.pt
ideabox/policy/content/__init__.py
ideabox/policy/content/campaign.py
ideabox/policy/content/configure.zcml
ideabox/policy/content/indexer.py
ideabox/policy/content/priority_action.py
ideabox/policy/content/project.pt
ideabox/policy/content/project.py
ideabox/policy/content/state_progress.pt
ideabox/policy/content/state_progress.py
ideabox/policy/content/subscriber.py
ideabox/policy/content/syndication.py
ideabox/policy/data/taxonomy-settings-district.xml
ideabox/policy/data/taxonomy-settings-iam.xml
ideabox.policy-3.4.18.dist-info/LICENSE.GPL
ideabox.policy-3.4.18.dist-info/LICENSE.rst
ideabox.policy-3.4.18.dist-info/METADATA
ideabox.policy-3.4.18.dist-info/WHEEL
ideabox.policy-3.4.18.dist-info/entry_points.txt
ideabox.policy-3.4.18.dist-info/namespace_packages.txt
ideabox.policy-3.4.18.dist-info/top_level.txt
ideabox.policy-3.4.18.dist-info/RECORD
