Metadata-Version: 2.1
Name: ideabox.policy
Version: 3.4.18
Summary: IdeaBox
Home-page: https://pypi.python.org/pypi/ideabox.policy
Author: Martin Peeters
Author-email: martin.peeters@affinitic.be
License: GPL version 2
Keywords: Python Plone
Classifier: Environment :: Web Environment
Classifier: Framework :: Plone
Classifier: Framework :: Plone :: 5.2
Classifier: Programming Language :: Python
Classifier: Programming Language :: Python :: 3
Classifier: Operating System :: OS Independent
Classifier: License :: OSI Approved :: GNU General Public License v2 (GPLv2)
License-File: LICENSE.GPL
License-File: LICENSE.rst
Requires-Dist: Products.GenericSetup (>=1.8.2)
Requires-Dist: Products.BeakerSessionDataManager
Requires-Dist: cioppino.twothumbs
Requires-Dist: collective.anonymouseditpatterns
Requires-Dist: collective.behavior.banner
Requires-Dist: collective.behavior.richdescription
Requires-Dist: collective.big.bang
Requires-Dist: collective.excelexport
Requires-Dist: collective.disclaimer
Requires-Dist: collective.faceted.map (>=1.0b7)
Requires-Dist: collective.taxonomy
Requires-Dist: collective.z3cform.datetimewidget
Requires-Dist: collective.z3cform.select2
Requires-Dist: iaweb.mosaic
Requires-Dist: ideabox.diazotheme.spirit
Requires-Dist: ideabox.theme
Requires-Dist: ideabox.stats
Requires-Dist: ideabox.restapi
Requires-Dist: imio.gdpr
Requires-Dist: pas.plugins.imio
Requires-Dist: password-generator
Requires-Dist: plone.api
Requires-Dist: plone.app.discussion
Requires-Dist: plone.app.imagecropping
Requires-Dist: plone.app.mosaic
Requires-Dist: plone.dexterity
Requires-Dist: plone.formwidget.geolocation
Requires-Dist: setuptools
Requires-Dist: z3c.jbot
Provides-Extra: test
Requires-Dist: plone.app.testing ; extra == 'test'
Requires-Dist: plone.testing ; extra == 'test'
Requires-Dist: plone.app.robotframework[debug] ; extra == 'test'
